LICENSE-CC-BY-SA-3.0-Unported
LICENSE-GPLv3
MANIFEST.in
README.rst
setup.py
conntrackt/__init__.py
conntrackt/admin.py
conntrackt/forms.py
conntrackt/iptables.py
conntrackt/models.py
conntrackt/urls.py
conntrackt/utils.py
conntrackt/views.py
conntrackt/migrations/0001_initial.py
conntrackt/migrations/0002_auto__add_unique_communication_source_destination_protocol_port.py
conntrackt/migrations/0003_auto__add_unique_entity_project_name__add_unique_location_name__add_un.py
conntrackt/migrations/0004_auto__add_unique_interface_netmask_address_entity.py
conntrackt/migrations/__init__.py
conntrackt/static/conntrackt.js
conntrackt/static/custom.css
conntrackt/static/jquery-min.js
conntrackt/static/bootstrap/css/bootstrap-responsive.css
conntrackt/static/bootstrap/css/bootstrap-responsive.min.css
conntrackt/static/bootstrap/css/bootstrap.css
conntrackt/static/bootstrap/css/bootstrap.min.css
conntrackt/static/bootstrap/img/glyphicons-halflings-white.png
conntrackt/static/bootstrap/img/glyphicons-halflings.png
conntrackt/static/bootstrap/js/bootstrap.js
conntrackt/static/bootstrap/js/bootstrap.min.js
conntrackt/templates/403.html
conntrackt/templates/admin/conntrackt/communication/change_list.html
conntrackt/templates/conntrackt/base.html
conntrackt/templates/conntrackt/create_form.html
conntrackt/templates/conntrackt/delete_form.html
conntrackt/templates/conntrackt/entity_detail.html
conntrackt/templates/conntrackt/entity_iptables.html
conntrackt/templates/conntrackt/index.html
conntrackt/templates/conntrackt/location_widget.html
conntrackt/templates/conntrackt/login.html
conntrackt/templates/conntrackt/project_detail.html
conntrackt/templates/conntrackt/project_widget.html
conntrackt/templates/conntrackt/search.html
conntrackt/templates/conntrackt/update_form.html
conntrackt/templatetags/__init__.py
conntrackt/templatetags/conntrackt_tags.py
conntrackt/tests/__init__.py
conntrackt/tests/factories.py
conntrackt/tests/forms.py
conntrackt/tests/helpers.py
django_conntrackt.egg-info/PKG-INFO
django_conntrackt.egg-info/SOURCES.txt
django_conntrackt.egg-info/dependency_links.txt
django_conntrackt.egg-info/requires.txt
django_conntrackt.egg-info/top_level.txt
