Metadata-Version: 1.1
Name: django-conntrackt
Version: 0.3.0
Summary: A simple application for tracking connection requirements between different entities in a network.
Home-page: http://projects.majic.rs/conntrackt
Author: Branko Majic
Author-email: branko@majic.rs
License: GPLv3+
Platform: UNKNOWN
Classifier: Development Status :: 4 - Beta
Classifier: Environment :: Web Environment
Classifier: Framework :: Django
Classifier: Intended Audience :: System Administrators
Classifier: License :: OSI Approved :: GNU General Public License v3 or later (GPLv3+)
Classifier: Operating System :: OS Independent
Classifier: Programming Language :: Python :: 2.7
Classifier: Topic :: Internet :: WWW/HTTP
Classifier: Topic :: Internet :: WWW/HTTP :: Dynamic Content
Classifier: Topic :: System :: Networking :: Firewalls
